{
  "$schema": "https://developer.microsoft.com/json-schemas/fabric/item/report/definition/visualContainer/2.8.0/schema.json",
  "name": "cbb4354cc588308bbdd0",
  "position": {
    "x": 753.94960303762514,
    "y": 140.7690714532275,
    "z": 19000,
    "height": 26.245081118398346,
    "width": 28.630997583707284,
    "tabOrder": 19000
  },
  "visual": {
    "visualType": "image",
    "objects": {
      "image": [
        {
          "properties": {
            "sourceFile": {
              "image": {
                "name": {
                  "expr": {
                    "Literal": {
                      "Value": "'Gemini_Generated_Image_l8ce6yl8ce6yl8ce-removebg-preview.png'"
                    }
                  }
                },
                "url": {
                  "expr": {
                    "ResourcePackageItem": {
                      "PackageName": "RegisteredResources",
                      "PackageType": 1,
                      "ItemName": "Gemini_Generated_Image_l8ce6yl9505795823683065.png"
                    }
                  }
                },
                "scaling": {
                  "expr": {
                    "Literal": {
                      "Value": "'Normal'"
                    }
                  }
                }
              }
            },
            "fit": {
              "expr": {
                "Literal": {
                  "Value": "'Fill'"
                }
              }
            }
          }
        }
      ]
    },
    "drillFilterOtherVisuals": true
  }
}